[
  {
    "kind": "ObjectStorage",
    "version": 1,
    "id": "c688c143-6575-4a54-b00b-e81f7dc22f3c",
    "name": "policy_os_7478_us_group_3_cjj0",
    "modeled_policy": [
      {
        "version": 1,
        "id": "ca368e22-4a2b-4daa-802b-112e3b81389d",
        "input_policy": {
          "actions": [
            "ListObjects",
            "ListParts",
            "HeadObject",
            "GetObject",
            "PutObject",
            "CopyObject",
            "ListMultiPartUploads",
            "CreateMultipartUpload",
            "AbortMultipartUpload",
            "CompleteMultipartUpload",
            "UploadPart",
            "GetBucketTagging",
            "PutBucketTagging",
            "DeleteObject"
          ],
          "bucket": {
            "name": {
              "eq": [
                "data-processing-data"
              ]
            },
            "allow": {},
            "keys": [
              {
                "allow": {}
              }
            ]
          }
        }
      }
    ]
  },
  {
    "kind": "ObjectStorage",
    "version": 1,
    "id": "1504a97e-bd1d-4e5a-9397-7f2f7764a188",
    "name": "policy_os_3977_cn_group_3_shf0",
    "modeled_policy": [
      {
        "version": 1,
        "id": "46cfbfb7-2104-4d09-96bd-1338a94366be",
        "input_policy": {
          "actions": [
            "ListObjects",
            "ListParts",
            "HeadObject",
            "GetObject",
            "PutObject",
            "CopyObject",
            "ListMultiPartUploads",
            "CreateMultipartUpload",
            "AbortMultipartUpload",
            "CompleteMultipartUpload",
            "UploadPart",
            "GetBucketTagging",
            "PutBucketTagging",
            "DeleteObject"
          ],
          "bucket": {
            "name": {
              "eq": [
                "datalake-internal.patsnap.com-cn-northwest-1"
              ]
            },
            "allow": {},
            "keys": [
              {
                "allow": {}
              }
            ]
          }
        }
      }
    ]
  },
  {
    "kind": "ObjectStorage",
    "version": 1,
    "id": "d3337c4b-33df-47be-980b-6dd31a67ca1b",
    "name": "policy_os_3977_cn_group_3_qwt0",
    "modeled_policy": [
      {
        "version": 1,
        "id": "8aaba6e7-0ad9-469f-9713-0c73c12b927e",
        "input_policy": {
          "actions": [
            "ListObjects",
            "ListParts",
            "HeadObject",
            "GetObject",
            "PutObject",
            "CopyObject",
            "ListMultiPartUploads",
            "CreateMultipartUpload",
            "AbortMultipartUpload",
            "CompleteMultipartUpload",
            "UploadPart",
            "GetBucketTagging",
            "PutBucketTagging"
          ],
          "bucket": {
            "name": {
              "eq": [
                "patsnap-country-source-1251949819"
              ]
            },
            "allow": {},
            "keys": [
              {
                "allow": {}
              }
            ]
          }
        }
      }
    ]
  },
  {
    "kind": "ObjectStorage",
    "version": 1,
    "id": "af6ac00e-914a-4683-9e84-04513f8c92d4",
    "name": "policy_os_4258_us_group_3_fxd0",
    "modeled_policy": [
      {
        "version": 1,
        "id": "19b81e6d-ea2f-44a6-ac36-74bdbee1190f",
        "input_policy": {
          "actions": [
            "ListObjects",
            "ListParts",
            "HeadObject",
            "GetObject",
            "PutObject",
            "CopyObject",
            "ListMultiPartUploads",
            "CreateMultipartUpload",
            "AbortMultipartUpload",
            "CompleteMultipartUpload",
            "UploadPart",
            "GetBucketTagging",
            "PutBucketTagging"
          ],
          "bucket": {
            "name": {
              "eq": [
                "patsnap-country-source-1251949819"
              ]
            },
            "allow": {},
            "keys": [
              {
                "allow": {}
              }
            ]
          }
        }
      }
    ]
  },
  {
    "kind": "ObjectStorage",
    "version": 1,
    "id": "c9f3b3f1-3b1a-4b0f-8b1a-3b1a4b0f8b1a",
    "name": "policy_os_0066_us_group_3_zsz0",
    "modeled_policy": [
      {
        "version": 1,
        "id": "c9c250d6-95a9-4f22-be41-78bdae330d7a",
        "input_policy": {
          "actions": [
            "ListObjects",
            "ListParts",
            "HeadObject",
            "GetObject",
            "PutObject",
            "CopyObject",
            "ListMultiPartUploads",
            "CreateMultipartUpload",
            "AbortMultipartUpload",
            "CompleteMultipartUpload",
            "UploadPart",
            "GetBucketTagging",
            "PutBucketTagging"
          ],
          "bucket": {
            "name": {
              "eq": [
                "patsnap-country-source",
                "testpatsnapus"
              ]
            },
            "allow": {},
            "keys": [
              {
                "allow": {}
              }
            ]
          }
        }
      }
    ]
  },
  {
    "kind": "ObjectStorage",
    "version": 1,
    "id": "b41a95b9-fbb7-41ca-9392-69fc6928f592",
    "name": "policy_os_4258_us_group_3_zsz0",
    "modeled_policy": [
      {
        "version": 1,
        "id": "053e952b-a03f-453d-b9a3-a6c9d784d740",
        "input_policy": {
          "actions": [
            "ListObjects",
            "ListParts",
            "HeadObject",
            "GetObject",
            "PutObject",
            "CopyObject",
            "ListMultiPartUploads",
            "CreateMultipartUpload",
            "AbortMultipartUpload",
            "CompleteMultipartUpload",
            "UploadPart",
            "GetBucketTagging",
            "PutBucketTagging"
          ],
          "bucket": {
            "name": {
              "eq": [
                "patsnap-country-source-1251949819"
              ]
            },
            "allow": {},
            "keys": [
              {
                "allow": {}
              }
            ]
          }
        }
      }
    ]
  },
  {
    "kind": "ObjectStorage",
    "version": 1,
    "id": "fca756ea-042d-40d9-857d-0861147cdae7",
    "name": "policy_os_0066_us_group_3_whl0",
    "modeled_policy": [
      {
        "version": 1,
        "id": "60b8ac47-2e10-4410-a593-8f4805e8074f",
        "input_policy": {
          "actions": [
            "ListObjects",
            "ListParts",
            "HeadObject",
            "GetObject",
            "PutObject",
            "CopyObject",
            "ListMultiPartUploads",
            "CreateMultipartUpload",
            "AbortMultipartUpload",
            "CompleteMultipartUpload",
            "UploadPart",
            "GetBucketTagging",
            "PutBucketTagging"
          ],
          "bucket": {
            "name": {
              "eq": [
                "testpatsnapus"
              ]
            },
            "allow": {},
            "keys": [
              {
                "allow": {}
              }
            ]
          }
        }
      }
    ]
  },
  {
    "kind": "ObjectStorage",
    "version": 1,
    "id": "357DD2B7-268D-49D2-858F-1CA574739CE0",
    "name": "policy_os_7478_us_east00000_1_group_sa_dev",
    "modeled_policy": [
      {
        "version": 0,
        "id": "A158CB2A-D56D-4F1B-9A87-635D2B789149",
        "input_policy": {
          "actions": [
            "ListObjects",
            "ListParts",
            "HeadObject",
            "GetObject",
            "PutObject",
            "CopyObject",
            "ListMultiPartUploads",
            "CreateMultipartUpload",
            "AbortMultipartUpload",
            "CompleteMultipartUpload",
            "UploadPart",
            "GetBucketTagging",
            "PutBucketTagging"
          ],
          "bucket": {
            "name": {
              "eq": [
                "aws-athena-query-results-747875099153-us-east-1",
                "data-processing-data",
                "data-image-cn-northwest-1",
                "data-image-us-east-1",
                "data-sync-logs-patsnap-us-east-1",
                "datalake-internal.patsnap.com",
                "rnd-image-test",
                "rnd-internal-us-east-1.patsnap.com",
                "rnd-internal-us-east-1",
                "patsnap-general-source",
                "patsnap-sa-data",
                "pdf-patsnap-us-east-1",
                "search-us-east-1-prod",
                "patsnaprd-cv-prod-us-east-1",
                "data-filewrapper-patsnap-us-east-1"
              ]
            },
            "allow": {},
            "keys": [
              {
                "allow": {}
              }
            ]
          }
        }
      }
    ]
  },
  {
    "kind": "ObjectStorage",
    "version": 1,
    "id": "B64AC16F-D9AA-47AD-9DDD-30055FC0DD9C",
    "name": "policy_os_3977_cn_northwest_1_group_sa_dev",
    "modeled_policy": [
      {
        "version": 0,
        "id": "04DD8391-A013-405C-A3CD-2BC490DC6C27",
        "input_policy": {
          "actions": [
            "ListObjects",
            "ListParts",
            "HeadObject",
            "GetObject",
            "PutObject",
            "CopyObject",
            "ListMultiPartUploads",
            "CreateMultipartUpload",
            "AbortMultipartUpload",
            "CompleteMultipartUpload",
            "UploadPart",
            "GetBucketTagging",
            "PutBucketTagging"
          ],
          "bucket": {
            "name": {
              "eq": [
                "data-pdf-cn-northwest-1",
                "chemical-upload-images-cn-northwest-1",
                "data-fulltextimage-cn-northwest-1",
                "data-fulltextimage240-cn-northwest-1",
                "data-image-cn-northwest-1",
                "data-image120-cn-northwest-1",
                "data-imagesearch-cn-northwest-1",
                "data-page-image-cn-northwest-1",
                "data-page-image240-cn-northwest-1",
                "data-pdf-images-cn-northwest-1",
                "data-trademark-image-cn-northwest-1",
                "data-trademarkimage-cn-northwest-1",
                "landscape-image-cn-northwest-1",
                "data-country-source-cn-northwest-1",
                "patsnaprd-cv-prod-cn-northwest-1"
              ]
            },
            "allow": {},
            "keys": [
              {
                "allow": {}
              }
            ]
          }
        }
      }
    ]
  },
  {
    "kind": "ObjectStorage",
    "version": 1,
    "id": "5fff622c-7c1c-4773-8ee5-07508d2e24d2",
    "name": "policy_os_0066_us_east00000_1_group_team_sa_dev",
    "modeled_policy": [
      {
        "version": 1,
        "id": "94fc1781-f0fc-4660-a9f3-26f73eb8e420",
        "input_policy": {
          "actions": [
            "ListObjects",
            "ListParts",
            "HeadObject",
            "GetObject",
            "PutObject",
            "CopyObject",
            "ListMultiPartUploads",
            "CreateMultipartUpload",
            "AbortMultipartUpload",
            "CompleteMultipartUpload",
            "UploadPart",
            "GetBucketTagging",
            "PutBucketTagging"
          ],
          "bucket": {
            "name": {
              "eq": [
                "patsnap-country-source",
                "testpatsnapus"
              ]
            },
            "allow": {},
            "keys": [
              {
                "allow": {}
              }
            ]
          }
        }
      }
    ]
  },
  {
    "kind": "ObjectStorage",
    "version": 1,
    "id": "D91C0510-BF5E-4050-9651-E27A0CD1ACD1",
    "name": "policy_os_7478_us_east00000_1_group_team_data_dev",
    "modeled_policy": [
      {
        "version": 1,
        "id": "363700F4-F590-42D8-B7FA-C44651DBFF91",
        "input_policy": {
          "actions": [
            "ListObjects",
            "ListParts",
            "HeadObject",
            "GetObject",
            "PutObject",
            "CopyObject",
            "ListMultiPartUploads",
            "CreateMultipartUpload",
            "AbortMultipartUpload",
            "CompleteMultipartUpload",
            "UploadPart",
            "GetBucketTagging",
            "PutBucketTagging"
          ],
          "bucket": {
            "name": {
              "eq": [
                "data-processing-data",
                "datalake-internal.patsnap.com",
                "360-npl-patsnap-us-east-1",
                "data-sync-logs-patsnap-us-east-1",
                "datalake-internal.patsnap.com",
                "testpatsnapus"
              ]
            },
            "allow": {},
            "keys": [
              {
                "allow": {}
              }
            ]
          }
        }
      }
    ]
  },
  {
    "kind": "ObjectStorage",
    "version": 1,
    "id": "E8AD189E-3DDE-4C89-BD9D-3DC1676C2355",
    "name": "policy_os_3977_cn_northwest_1_group_team_data_dev",
    "modeled_policy": [
      {
        "version": 1,
        "id": "2CD54225-06EB-43C1-A276-05F05088E4FC",
        "input_policy": {
          "actions": [
            "ListObjects",
            "ListParts",
            "HeadObject",
            "GetObject",
            "PutObject",
            "CopyObject",
            "ListMultiPartUploads",
            "CreateMultipartUpload",
            "AbortMultipartUpload",
            "CompleteMultipartUpload",
            "UploadPart",
            "GetBucketTagging",
            "PutBucketTagging"
          ],
          "bucket": {
            "name": {
              "eq": [
                "datalake-internal.patsnap.com-cn-northwest-1",
                "data-country-source-cn-northwest-1",
                "data-oplog-cn-northwest-1"
              ]
            },
            "allow": {},
            "keys": [
              {
                "allow": {}
              }
            ]
          }
        }
      }
    ]
  },
  {
    "kind": "ObjectStorage",
    "version": 1,
    "id": "F06FA0B9-05E4-42DE-A4B1-74927303A54E",
    "name": "policy_os_0066_us_east00000_1_group_team_data_dev",
    "modeled_policy": [
      {
        "version": 1,
        "id": "ECCA678E-9892-4F3E-8879-7A8EC2E2F262",
        "input_policy": {
          "actions": [
            "ListObjects",
            "ListParts",
            "HeadObject",
            "GetObject",
            "PutObject",
            "CopyObject",
            "ListMultiPartUploads",
            "CreateMultipartUpload",
            "AbortMultipartUpload",
            "CompleteMultipartUpload",
            "UploadPart",
            "GetBucketTagging",
            "PutBucketTagging"
          ],
          "bucket": {
            "name": {
              "eq": [
                "patsnap-country-source",
                "testpatsnapus",
                "patsnap-general-source"
              ]
            },
            "allow": {},
            "keys": [
              {
                "allow": {}
              }
            ]
          }
        }
      }
    ]
  },
  {
    "kind": "ObjectStorage",
    "version": 1,
    "id": "832F4043-C375-40FA-9FD4-1DE8B56E6821",
    "name": "policy_os_4258_na_ashburn0000_group_team_data_dev",
    "modeled_policy": [
      {
        "version": 1,
        "id": "8E2B6016-78B1-494E-979E-701F4D4D33B8",
        "input_policy": {
          "actions": [
            "ListObjects",
            "ListParts",
            "HeadObject",
            "GetObject",
            "PutObject",
            "CopyObject",
            "ListMultiPartUploads",
            "CreateMultipartUpload",
            "AbortMultipartUpload",
            "CompleteMultipartUpload",
            "UploadPart",
            "GetBucketTagging",
            "PutBucketTagging"
          ],
          "bucket": {
            "name": {
              "eq": [
                "patsnap-country-source-1251949819",
                "patsnap-general-source-1251949819",
                "data-npd-attachment-prod-us-1251949819",
                "npd-1251949819",
                "data-npd-attachment-prod-cn-1251949819"
              ]
            },
            "allow": {},
            "keys": [
              {
                "allow": {}
              }
            ]
          }
        }
      }
    ]
  },
  {
    "kind": "ObjectStorage",
    "version": 1,
    "id": "9d216c69-d9db-4720-8146-c5b2be6681bb",
    "name": "policy_os_7478_us_east00000_1_group_team_data_services",
    "modeled_policy": [
      {
        "version": 0,
        "id": "63ae2d4c-5165-47ef-bcd7-203fc83b130a",
        "input_policy": {
          "actions": [
            "ListObjects",
            "ListParts",
            "HeadObject",
            "GetObject",
            "PutObject",
            "CopyObject",
            "ListMultiPartUploads",
            "CreateMultipartUpload",
            "AbortMultipartUpload",
            "CompleteMultipartUpload",
            "UploadPart",
            "GetBucketTagging",
            "PutBucketTagging"
          ],
          "bucket": {
            "name": {
              "eq": [
                "discovery-attachment-us-east-1",
                "datalake-internal.patsnap.com"
              ]
            },
            "allow": {},
            "keys": [
              {
                "allow": {}
              }
            ]
          }
        }
      }
    ]
  },
  {
    "kind": "ObjectStorage",
    "version": 1,
    "id": "E26CE826-6EEA-48FE-B71E-BB9B76CC0942",
    "name": "policy_os_7478_us_east00000_1_group_team_data_services_local",
    "modeled_policy": [
      {
        "version": 0,
        "id": "58AC18D4-0179-4EE6-A85B-7EE5BCAE5AD3",
        "input_policy": {
          "actions": [
            "ListObjects",
            "ListParts",
            "HeadObject",
            "GetObject",
            "PutObject",
            "CopyObject",
            "ListMultiPartUploads",
            "CreateMultipartUpload",
            "AbortMultipartUpload",
            "CompleteMultipartUpload",
            "UploadPart",
            "GetBucketTagging",
            "PutBucketTagging"
          ],
          "bucket": {
            "name": {
              "eq": [
                "datalake-internal.patsnap.com"
              ]
            },
            "allow": {},
            "keys": [
              {
                "allow": {}
              }
            ]
          }
        }
      }
    ]
  },
  {
    "kind": "ObjectStorage",
    "version": 1,
    "id": "ba8cf2e6-ed3e-4c32-a054-48d86abee06e",
    "name": "policy_os_3977_cn_northwest_1_group_team_data_services",
    "modeled_policy": [
      {
        "version": 0,
        "id": "944bf4ba-7618-4d28-9eda-52f9ef1750f0",
        "input_policy": {
          "actions": [
            "ListObjects",
            "ListParts",
            "HeadObject",
            "GetObject",
            "PutObject",
            "CopyObject",
            "ListMultiPartUploads",
            "CreateMultipartUpload",
            "AbortMultipartUpload",
            "CompleteMultipartUpload",
            "UploadPart",
            "GetBucketTagging",
            "PutBucketTagging"
          ],
          "bucket": {
            "name": {
              "eq": [
                "data-pdf-cn-northwest-1",
                "data-page-cn-northwest-1",
                "data-page120-cn-northwest-1",
                "data-image-cn-northwest-1",
                "data-image120-cn-northwest-1",
                "data-fulltextimage-cn-northwest-1",
                "data-fulltextimage240-cn-northwest-1",
                "data-page-image-cn-northwest-1",
                "data-page-image240-cn-northwest-1"
              ]
            },
            "allow": {},
            "keys": [
              {
                "allow": {}
              }
            ]
          }
        }
      }
    ]
  },
  {
    "kind": "ObjectStorage",
    "version": 1,
    "id": "00a85912-02cc-40cd-8f0c-baed0409f23b",
    "name": "policy_os_0066_us_east00000_1_group_team_data_services",
    "modeled_policy": [
      {
        "version": 0,
        "id": "1ff4803e-7745-47ad-a11e-f6c62595db49",
        "input_policy": {
          "actions": [
            "ListObjects",
            "ListParts",
            "HeadObject",
            "GetObject",
            "PutObject",
            "CopyObject",
            "ListMultiPartUploads",
            "CreateMultipartUpload",
            "AbortMultipartUpload",
            "CompleteMultipartUpload",
            "UploadPart",
            "GetBucketTagging",
            "PutBucketTagging",
            "DeleteObject"
          ],
          "bucket": {
            "allow": {},
            "keys": [
              {
                "allow": {}
              }
            ]
          }
        }
      }
    ]
  },
  {
    "kind": "ObjectStorage",
    "version": 1,
    "id": "8be9190d-e7b1-4398-ae62-95afc5c69b0b",
    "name": "policy_os_4258_na_ashburn0000_group_team_data_services",
    "modeled_policy": [
      {
        "version": 0,
        "id": "81eec3f4-a4d4-46f0-97fe-10635a2f8632",
        "input_policy": {
          "actions": [
            "ListObjects",
            "ListParts",
            "HeadObject",
            "GetObject",
            "PutObject",
            "CopyObject",
            "ListMultiPartUploads",
            "CreateMultipartUpload",
            "AbortMultipartUpload",
            "CompleteMultipartUpload",
            "UploadPart",
            "GetBucketTagging",
            "PutBucketTagging",
            "DeleteObject"
          ],
          "bucket": {
            "name": {
              "eq": [
                "patsnap-country-source-1251949819"
              ]
            },
            "allow": {},
            "keys": [
              {
                "allow": {}
              }
            ]
          }
        }
      }
    ]
  },
  {
    "kind": "ObjectStorage",
    "version": 1,
    "id": "05e75fbf-81dc-4962-9c78-9bab8d4fc926",
    "name": "policy_os_opst_for_all",
    "modeled_policy": [
      {
        "version": 0,
        "id": "23b22c98-b71b-41ad-93bf-fcdb72700d98",
        "input_policy": {
          "actions": [
            "ListObjects",
            "ListParts",
            "HeadObject",
            "GetObject",
            "PutObject",
            "CopyObject",
            "ListMultiPartUploads",
            "CreateMultipartUpload",
            "AbortMultipartUpload",
            "CompleteMultipartUpload",
            "UploadPart",
            "GetBucketTagging",
            "PutBucketTagging",
            "DeleteObject"
          ],
          "bucket": {
            "allow": {},
            "keys": [
              {
                "allow": {}
              }
            ]
          }
        }
      }
    ]
  },
  {
    "kind": "ObjectStorage",
    "version": 1,
    "id": "bd4558d4-c0d6-4045-afd5-902d6714c021",
    "name": "policy_os_7478_us_east00000_1_group_data_tmp",
    "modeled_policy": [
      {
        "version": 0,
        "id": "c114362f-aa1a-4cfc-8b5d-5eca3d37b068",
        "input_policy": {
          "actions": [
            "ListObjects",
            "ListParts",
            "HeadObject",
            "GetObject",
            "PutObject",
            "CopyObject",
            "ListMultiPartUploads",
            "CreateMultipartUpload",
            "AbortMultipartUpload",
            "CompleteMultipartUpload",
            "UploadPart",
            "GetBucketTagging",
            "PutBucketTagging"
          ],
          "bucket": {
            "allow": {},
            "keys": [
              {
                "allow": {}
              }
            ]
          }
        }
      }
    ]
  },
  {
    "kind": "ObjectStorage",
    "version": 1,
    "id": "35b1e920-0856-4965-aed4-7ced267ee4d5",
    "name": "policy_os_3977_cn_northwest_1_group_data_tmp",
    "modeled_policy": [
      {
        "version": 0,
        "id": "238925f9-9a61-4cc1-ac04-712c42f14ff6",
        "input_policy": {
          "actions": [
            "ListObjects",
            "ListParts",
            "HeadObject",
            "GetObject",
            "PutObject",
            "CopyObject",
            "ListMultiPartUploads",
            "CreateMultipartUpload",
            "AbortMultipartUpload",
            "CompleteMultipartUpload",
            "UploadPart",
            "GetBucketTagging",
            "PutBucketTagging"
          ],
          "bucket": {
            "allow": {},
            "keys": [
              {
                "allow": {}
              }
            ]
          }
        }
      }
    ]
  },
  {
    "kind": "ObjectStorage",
    "version": 1,
    "id": "5ADBA056-2EC1-4B6C-A8F4-B42245509180",
    "name": "policy_os_group_allow_all",
    "modeled_policy": [
      {
        "version": 0,
        "id": "36EADFB4-E229-4D73-9D79-BA0BCE997DDB",
        "input_policy": {
          "actions": [
            "ListObjects",
            "ListParts",
            "HeadObject",
            "GetObject",
            "PutObject",
            "CopyObject",
            "ListMultiPartUploads",
            "CreateMultipartUpload",
            "AbortMultipartUpload",
            "CompleteMultipartUpload",
            "UploadPart",
            "GetBucketTagging",
            "PutBucketTagging",
            "DeleteObject"
          ],
          "bucket": {
            "allow": {},
            "keys": [
              {
                "allow": {}
              }
            ]
          }
        }
      }
    ]
  }
]